{
	"version": 1,
	"license": "CC-BY-SA-3.0",
	"copyright": "Paradise Station/Starlight",
	"size": {
		"x": 32,
		"y": 32
	},
	"states": [
		{
			"name": "web",
			"copyright": "Paradise Station"
		},
		{
			"name": "lay_eggs",
			"copyright": "Taken from Paradise Station RU SS13, modified by Rinary1(GitHub) for Starlight SS14",
			"delays": [
				[
					0.2,
					0.2,
					0.2
				]
			]
		},
		{
			"name": "spiderscream",
			"copyright": "Starlight"
		},
		{
			"name": "evolve",
			"copyright": "Taken from Paradise Station SS13, modified by Rinary1(GitHub) for Starlight SS14"
		},
		{
			"name": "acid_vent",
			"copyright": "Taken from Paradise Station SS13, modified by Rinary1(GitHub) for Starlight SS14"
		},
		{
			"name": "wrap",
			"copyright": "Taken from Paradise Station SS13, modified by Rinary1(GitHub) for Starlight SS14"
		}
	]
}
